Metadata-Version: 2.1
Name: prg2xex
Version: 0.0.1
Summary: Convert KickAssembler prg object code to Atari 8 Bit xex file
Home-page: https://github.com/peckhamdata/prg2xex
Author: worldofchris
Author-email: chris@worldofchris.com
License: MIT
Platform: UNKNOWN
Classifier: Programming Language :: Python :: 3
Classifier: License :: OSI Approved :: MIT License
Classifier: Operating System :: OS Independent
Requires-Python: >=3.6
